alembic/versions/131aab4d9e49_create_tables.py
alembic/versions/407037cb1636_add_stac_1_0_0_fields.py
alembic/versions/5909bd10f2e6_change_item_geometry_column_type.py
alembic/versions/7016c1bf3fbf_make_item_geometry_and_bbox_nullable.py
alembic/versions/77c019af60bf_use_timestamptz_rather_than_timestamp.py
alembic/versions/821aa04011e8_change_pri_key_for_item.py
stac_fastapi/sqlalchemy/__init__.py
stac_fastapi/sqlalchemy/app.py
stac_fastapi/sqlalchemy/config.py
stac_fastapi/sqlalchemy/core.py
stac_fastapi/sqlalchemy/serializers.py
stac_fastapi/sqlalchemy/session.py
stac_fastapi/sqlalchemy/tokens.py
stac_fastapi/sqlalchemy/transactions.py
stac_fastapi/sqlalchemy/version.py
stac_fastapi/sqlalchemy/extensions/__init__.py
stac_fastapi/sqlalchemy/extensions/query.py
stac_fastapi/sqlalchemy/models/__init__.py
stac_fastapi/sqlalchemy/models/database.py
stac_fastapi/sqlalchemy/models/search.py
tests/api/__init__.py
tests/api/test_api.py
tests/clients/__init__.py
tests/clients/test_postgres.py
tests/features/__init__.py
tests/features/test_custom_models.py
tests/resources/__init__.py
tests/resources/test_collection.py
tests/resources/test_conformance.py
tests/resources/test_item.py
tests/resources/test_mgmt.py
stac_fastapi.sqlalchemy-2.4.5.dist-info/METADATA
stac_fastapi.sqlalchemy-2.4.5.dist-info/WHEEL
stac_fastapi.sqlalchemy-2.4.5.dist-info/entry_points.txt
stac_fastapi.sqlalchemy-2.4.5.dist-info/top_level.txt
stac_fastapi.sqlalchemy-2.4.5.dist-info/RECORD
