Metadata-Version: 2.1
Name: stac-fastapi.sqlalchemy
Version: 2.4.5
Summary: An implementation of STAC API based on the FastAPI framework.
Home-page: https://github.com/stac-utils/stac-fastapi
Author: Arturo Engineering
Author-email: engineering@arturo.ai
License: MIT
Keywords: STAC FastAPI COG
Classifier: Intended Audience :: Developers
Classifier: Intended Audience :: Information Technology
Classifier: Intended Audience :: Science/Research
Classifier: Programming Language :: Python :: 3.8
Classifier: License :: OSI Approved :: MIT License
Requires-Python: >=3.8
Requires-Dist: attrs
Requires-Dist: pydantic[dotenv]
Requires-Dist: stac-pydantic (>=2.0.3)
Requires-Dist: stac-fastapi.types
Requires-Dist: stac-fastapi.api
Requires-Dist: stac-fastapi.extensions
Requires-Dist: sqlakeyset
Requires-Dist: geoalchemy2 (<0.8.0)
Requires-Dist: sqlalchemy (==1.3.23)
Requires-Dist: shapely
Requires-Dist: psycopg2-binary
Requires-Dist: alembic
Requires-Dist: fastapi-utils
Provides-Extra: dev
Requires-Dist: pytest ; extra == 'dev'
Requires-Dist: pytest-cov ; extra == 'dev'
Requires-Dist: pre-commit ; extra == 'dev'
Requires-Dist: requests ; extra == 'dev'
Provides-Extra: docs
Requires-Dist: mkdocs ; extra == 'docs'
Requires-Dist: mkdocs-material ; extra == 'docs'
Requires-Dist: pdocs ; extra == 'docs'
Provides-Extra: server
Requires-Dist: uvicorn[standard] (==0.19.0) ; extra == 'server'
